Workbook
Name aporte: Painel!$D$13
Name patrimonio: Painel!$D$16
Name perfil: Painel!$G$7
Name qntd_anos: Painel!$D$14
Name rendimento_carteira: Painel!$D$9
Name taxa_mensal: Painel!$D$15
Name valor_sug: Painel!$G$8

Sheet Painel
C3: DIO INVEST
C5: Perguntas de Negócio
C7: CONFIGURAÇÕES | F7: PERFIL | G7: CONSERVADOR | H7: =_xlfn.XLOOKUP(G7,tbl_apoio!H:H,tbl_apoio!I:I) -> ★☆☆☆☆
C8: Salário | D8: 5000 | F8: Valor a ser investido p/mês | G8: =aporte -> 500 | H8: Grau
C9: Rendimento Carteira | D9: 0.01
C10: Sugestão de Investimento (30%) | D10: =D8*30% -> 1500 | F10: CENARIOS VARIÁVEIS | G10: V. ACUMULADO | H10: DIVIDENDOS
F11: Quanto em 2 anos? | G11: =FV(taxa_mensal,2*12,aporte*-1) -> 13615.432 | H11: =G11*rendimento_carteira -> 136.15432
C12: INVESTIMENTO MENSAL | F12: Quanto em 5 anos? | G12: =FV(taxa_mensal,5*12,aporte*-1) -> 41902.01 | H12: =G12*rendimento_carteira -> 419.0201
C13: Quanto investir por mês? | D13: 500 | F13: Quanto em 10 anos? | G13: =FV(taxa_mensal,10*12,aporte*-1) -> 121728.83 | H13: =G13*rendimento_carteira -> 1217.2883
C14: Por Quantos Anos? | D14: 1 | F14: Quanto em 20 anos? | G14: =FV(taxa_mensal,20*12,aporte*-1) -> 563524.5 | H14: =G14*rendimento_carteira -> 5635.245
C15: Taxa de Rendimento Mensal? | D15: 0.0108 | F15: Quanto em 30 anos? | G15: =FV(taxa_mensal,30*12,aporte*-1) -> 2166952.4 | H15: =G15*rendimento_carteira -> 21669.524
C16: Patrimônio Acumulado? | D16: =FV(taxa_mensal,qntd_anos*12,aporte*-1) -> 6369.5476
C17: Dividendos Mensais? | D17: =patrimonio*1% -> 63.695476
C19: Tipo de FII | D19: % Sugerido | E19: Valores
C20: Papel | D20: =_xlfn.XLOOKUP(perfil&C20,tbl_apoio!A:A,tbl_apoio!D:D) -> 0.3 | E20: =aporte*D20 -> 150
C21: Tijolo | D21: =_xlfn.XLOOKUP(perfil&C21,tbl_apoio!A:A,tbl_apoio!D:D) -> 0.5 | E21: =aporte*D21 -> 250
C22: Híbridos | D22: =_xlfn.XLOOKUP(perfil&C22,tbl_apoio!A:A,tbl_apoio!D:D) -> 0.1 | E22: =aporte*D22 -> 50
C23: Fofs | D23: =_xlfn.XLOOKUP(perfil&C23,tbl_apoio!A:A,tbl_apoio!D:D) -> 0.1 | E23: =aporte*D23 -> 50
C24: Desenvolvimento | D24: =_xlfn.XLOOKUP(perfil&C24,tbl_apoio!A:A,tbl_apoio!D:D) -> 0 | E24: =aporte*D24 -> 0
C25: Hotelarias | D25: =_xlfn.XLOOKUP(perfil&C25,tbl_apoio!A:A,tbl_apoio!D:D) -> 0 | E25: =aporte*D25 -> 0
C26: Total | E26: =SUM(E20:E25) -> 500

Sheet tbl_apoio
A1: Chave | B1: Perfil | C1: Tipo de FII | D1: % | H1: {=_xlfn.UNIQUE(B:B)} -> Perfil | I1: Grau
A2: =B2&C2 -> ConservadorPAPEL | B2: Conservador | C2: PAPEL | D2: 0.3 | H2: Conservador | I2: ★☆☆☆☆
A3: =B3&C3 -> ConservadorTIJOLO | B3: Conservador | C3: TIJOLO | D3: 0.5 | H3: Moderado | I3: ★★★☆☆
A4: =B4&C4 -> ConservadorHÍBRIDOS | B4: Conservador | C4: HÍBRIDOS | D4: 0.1 | H4: Agressivo | I4: ★★★★★
A5: =B5&C5 -> ConservadorFOFs | B5: Conservador | C5: FOFs | D5: 0.1 | H5: 0
A6: =B6&C6 -> ConservadorDESENVOLVIMENTO | B6: Conservador | C6: DESENVOLVIMENTO | D6: 0
A7: =B7&C7 -> ConservadorHOTELARIAS | B7: Conservador | C7: HOTELARIAS | D7: 0
A8: =B8&C8 -> ModeradoPAPEL | B8: Moderado | C8: PAPEL | D8: 0.32
A9: =B9&C9 -> ModeradoTIJOLO | B9: Moderado | C9: TIJOLO | D9: 0.35
A10: =B10&C10 -> ModeradoHÍBRIDOS | B10: Moderado | C10: HÍBRIDOS | D10: 0.08
A11: =B11&C11 -> ModeradoFOFs | B11: Moderado | C11: FOFs | D11: 0.05
A12: =B12&C12 -> ModeradoDESENVOLVIMENTO | B12: Moderado | C12: DESENVOLVIMENTO | D12: 0.1
A13: =B13&C13 -> ModeradoHOTELARIAS | B13: Moderado | C13: HOTELARIAS | D13: 0.1
A14: =B14&C14 -> AgressivoPAPEL | B14: Agressivo | C14: PAPEL | D14: 0.5
A15: =B15&C15 -> AgressivoTIJOLO | B15: Agressivo | C15: TIJOLO | D15: 0.1
A16: =B16&C16 -> AgressivoHÍBRIDOS | B16: Agressivo | C16: HÍBRIDOS | D16: 0.05
A17: =B17&C17 -> AgressivoFOFs | B17: Agressivo | C17: FOFs | D17: 0.05
... A19: =B19&C19 -> AgressivoHOTELARIAS | B19: Agressivo | C19: HOTELARIAS | D19: 0.1
